{"files": {"kid_admin_py": {"index": {"relative_filename": "kid\\admin.py", "html_filename": "kid_admin_py.html", "nums": [1, 23, 0, 23, 0, 0, 0]}, "hash": "27463599bf62a95b7babd81d8cc3345d"}, "kid_views_py": {"index": {"relative_filename": "kid\\views.py", "html_filename": "kid_views_py.html", "nums": [1, 333, 0, 178, 0, 0, 0]}, "hash": "96e49f1d7fcfddb291f3df3a1cd83aea"}, "kid_forms_py": {"index": {"relative_filename": "kid\\forms.py", "html_filename": "kid_forms_py.html", "nums": [1, 45, 0, 13, 0, 0, 0]}, "hash": "17d1348d6e4c8667277e87fe72ce25f4"}, "kid_py": {"index": {"relative_filename": "kid.py", "html_filename": "kid_py.html", "nums": [1, 0, 0, 0, 0, 0, 0]}, "hash": "19a064df3967067a2ec86c467e92d140"}, "kid_models_py": {"index": {"relative_filename": "kid\\models.py", "html_filename": "kid_models_py.html", "nums": [1, 44, 0, 41, 0, 0, 0]}, "hash": "e31987e7d162b48bfedac8f0f40c92d2"}, "kid_feed_py": {"index": {"relative_filename": "kid\\feed.py", "html_filename": "kid_feed_py.html", "nums": [1, 11, 0, 1, 0, 0, 0]}, "hash": "6b0fd23ce383fb1e55c782a7f584f335"}}, "version": "4.2", "settings": "5c65620afd8090ddb230fa9eb71d0eb6", "format": 1}